{"name":"aac","slug":"aac","count":1,"postlist":[{"title":"使用fdk-aac将iOS麦克风实时音频流编码为aac文件","uid":"09b66e066b45ce5ea1b53698890ec7ad","slug":"使用fdk-aac将iOS麦克风实时音频流编码为aac文件","date":"2016-09-07T16:58:20.000Z","updated":"2016-09-07T16:59:36.000Z","comments":true,"path":"api/articles/使用fdk-aac将iOS麦克风实时音频流编码为aac文件.json","keywords":null,"cover":null,"text":" iOS系统上的音频硬编码器，可实现将pcm音频数据编码为aac格式的数据。但是，对于低码率下的音频编码，就是它的软肋了。通过函数扫描iOS各系统上音频硬编码支持的情况发现，aac-lc编码都是支持的，苹果的官方文档也说的很清楚。对于aac-he-v2编码，iOS现在所有的系统都...","link":"","photos":[],"count_time":{"symbolsCount":952,"symbolsTime":"1 mins."},"categories":[{"name":"音视频开发","slug":"音视频开发","count":7,"path":"api/categories/音视频开发.json"}],"tags":[{"name":"fdk-aac","slug":"fdk-aac","count":1,"path":"api/tags/fdk-aac.json"},{"name":"aac","slug":"aac","count":1,"path":"api/tags/aac.json"}],"author":{"name":"William Xie","slug":"blog-author","avatar":"/img/author.png","link":"/","description":"","socials":{"github":"https://github.com/williamxiewz","twitter":"https://twitter.com/williamxie_wz","stackoverflow":"http://stackoverflow.com/users/4078104/goingxiebin-jobs","wechat":"","qq":"","weibo":"https://weibo.com/u/2281381063","zhihu":"https://www.zhihu.com/people/williamxiewz","csdn":"https://blog.csdn.net/u014222645","juejin":"https://juejin.cn/user/3280598430133277","customs":{}}}}]}